daniels/__init__.py
daniels/daniels.py
daniels-0.1.9.dist-info/LICENSE
daniels-0.1.9.dist-info/METADATA
daniels-0.1.9.dist-info/WHEEL
daniels-0.1.9.dist-info/top_level.txt
daniels-0.1.9.dist-info/RECORD
