Metadata-Version: 2.1
Name: daniels
Version: 0.1.9
Summary: Daniel, the autoreporter.
Home-page: https://github.com/harvested-financial/daniels
Author: Rory Gwozdz
Author-email: rory@harvestedfinancial.com
License: UNKNOWN
Keywords: pip,slack,daniel
Platform: UNKNOWN
Classifier: Programming Language :: Python :: 3
Classifier: License :: OSI Approved :: MIT License
Classifier: Operating System :: OS Independent
Requires-Python: >=3.6
Requires-Dist: slackclient
